pyfilemaker2/__init__.py
pyfilemaker2/caster.py
pyfilemaker2/data.py
pyfilemaker2/metadata.py
pyfilemaker2/parser.py
pyfilemaker2/server.py
pyfilemaker2/errors/__init__.py
pyfilemaker2/errors/errors_fms17.py
pyfilemaker2/tests/__init__.py
pyfilemaker2/tests/test_caster.py
pyfilemaker2/tests/test_data.py
pyfilemaker2/tests/test_metadata.py
pyfilemaker2/tests/test_server.py
pyfilemaker2/tests/ressources/TestFile.fmp12
pyfilemaker2/tests/ressources/__init__.py
pyfilemaker2/tests/ressources/dbnames.xml
pyfilemaker2/tests/ressources/fields_types.xml
pyfilemaker2/tests/ressources/layout_names.xml
pyfilemaker2/tests/ressources/non_ascii_chars.xml
pyfilemaker2/tests/ressources/scriptnames.xml
pyfilemaker2-0.2.1.dist-info/LICENSE.txt
pyfilemaker2-0.2.1.dist-info/METADATA
pyfilemaker2-0.2.1.dist-info/WHEEL
pyfilemaker2-0.2.1.dist-info/top_level.txt
pyfilemaker2-0.2.1.dist-info/RECORD
