Metadata-Version: 2.1
Name: pyfilemaker2
Version: 0.2.1
Summary: Python Object Wrapper for FileMaker Server XML Interface
Home-page: https://github.com/jeremie-borel/pyfilemaker2/
Author: Klokan Petr Pridal, Pieter Claerhout, Marcin Kawa, Jeremie Borel
Author-email: klokan@klokan.cz, pieter@yellowduck.be, kawa.macin@gmail.com
License: http://www.opensource.org/licenses/bsd-license.php
Download-URL: https://github.com/jeremie-borel/pyfilemaker2/
Keywords: FileMaker
Platform: any
Classifier: Environment :: Console
Classifier: Intended Audience :: Developers
Classifier: Intended Audience :: System Administrators
Classifier: License :: OSI Approved :: BSD License
Classifier: Programming Language :: Python :: 3.9
Classifier: Topic :: Database :: Database Engines/Servers
Classifier: Topic :: Software Development :: Libraries :: Python Modules
Requires-Dist: requests
Requires-Dist: lxml
